design.v
// Hamming Encoder Module (12,8)
module HammingEncoder(
    input [7:0] data_in,       // 8-bit input data
    output [11:0] encoded_data // 12-bit encoded data with parity bits
);
    wire p1, p2, p4, p8;

    // Calculate parity bits based on Hamming (12, 8) code rules
    assign p1 = data_in[0] ^ data_in[1] ^ data_in[3] ^ data_in[4] ^ data_in[6];
    assign p2 = data_in[0] ^ data_in[2] ^ data_in[3] ^ data_in[5] ^ data_in[6];
    assign p4 = data_in[1] ^ data_in[2] ^ data_in[3] ^ data_in[7];
    assign p8 = data_in[4] ^ data_in[5] ^ data_in[6] ^ data_in[7];

    // Assemble the encoded data with parity bits
    assign encoded_data = {p8, data_in[7:4], p4, data_in[3:1], p2, data_in[0], p1};
endmodule

// Hamming Decoder Module (12,8) with Error Detection and Correction
module HammingDecoder(
    input [11:0] encoded_data,  // 12-bit received encoded data
    output reg [7:0] data_out,  // 8-bit corrected data output
    output reg error_detected,  // Flag indicating an error was detected
    output reg error_corrected  // Flag indicating an error was corrected
);
    wire p1, p2, p4, p8;
    wire [3:0] syndrome;

    // Recalculate parity bits for error detection
    assign p1 = encoded_data[0] ^ encoded_data[2] ^ encoded_data[4] ^ encoded_data[6] ^ encoded_data[8] ^ encoded_data[10];
    assign p2 = encoded_data[1] ^ encoded_data[2] ^ encoded_data[5] ^ encoded_data[6] ^ encoded_data[9] ^ encoded_data[10];
    assign p4 = encoded_data[3] ^ encoded_data[4] ^ encoded_data[5] ^ encoded_data[6] ^ encoded_data[11];
    assign p8 = encoded_data[7] ^ encoded_data[8] ^ encoded_data[9] ^ encoded_data[10] ^ encoded_data[11];

    // Syndrome vector: indicates error location (if any)
    assign syndrome = {p8, p4, p2, p1};

    always @(encoded_data) begin
        if (syndrome == 4'b0000) begin
            // No error
            error_detected = 1'b0;
            error_corrected = 1'b0;
            data_out = encoded_data[10:3]; // Extract the original 8-bit data
        end else begin
            // Error detected, correct it
            error_detected = 1'b1;
            error_corrected = 1'b1;
            data_out = encoded_data[10:3] ^ (1 << (syndrome - 1)); // Correct the single-bit error
        end
    end
endmodule

// Memory Module with EDAC (Error Detection and Correction)
module MemoryEDAC(
    input [7:0] data_in,         // 8-bit data input
    input [3:0] address,         // 4-bit memory address
    input write_enable, read_enable,
    output [7:0] data_out,       // 8-bit corrected data output
    output error_detected,       // Flag for error detection
    output error_corrected       // Flag for error correction
);
    reg [11:0] memory [15:0];    // Memory array with 16 12-bit words (12 bits per word)

    // Intermediate signals
    wire [11:0] encoded_data;
    wire [7:0] decoded_data;
    wire detected_error, corrected_error;

    // Instantiate encoder and decoder modules
    HammingEncoder encoder(.data_in(data_in), .encoded_data(encoded_data));
    HammingDecoder decoder(.encoded_data(memory[address]), .data_out(decoded_data), .error_detected(detected_error), .error_corrected(corrected_error));

    // Write operation (store encoded data in memory)
    always @(posedge write_enable) begin
        memory[address] = encoded_data; // Write the encoded data to memory
    end

    // Read operation (retrieve and decode the data from memory)
    assign data_out = decoded_data;   // Get the corrected data from decoder
    assign error_detected = detected_error; // Set the error detection flag
    assign error_corrected = corrected_error; // Set the error correction flag
endmodule

testbench.v
module testbench;
    reg [7:0] data_in;        // 8-bit data input
    reg [3:0] address;        // 4-bit address input
    reg write_enable, read_enable;
    wire [7:0] data_out;      // 8-bit corrected data output
    wire error_detected, error_corrected;

    // Instantiate the MemoryEDAC module
    MemoryEDAC mem_edac(
        .data_in(data_in),
        .address(address),
        .write_enable(write_enable),
        .read_enable(read_enable),
        .data_out(data_out),
        .error_detected(error_detected),
        .error_corrected(error_corrected)
    );

    // Test sequence
    initial begin
        // Initialize signals
        data_in = 8'b10101010;
        address = 4'b0000;
        write_enable = 0;
        read_enable = 0;

        // Write data to memory
        #5 write_enable = 1; // Enable write operation
        #5 write_enable = 0; // Disable write operation
        
        // Simulate a read with no error
        #5 address = 4'b0000;  // Read from address 0
        #5 read_enable = 1;    // Enable read operation
        #5 read_enable = 0;    // Disable read operation

        // Simulate a read with a bit-flip error
        #5 mem_edac.memory[address] = 12'b101010101010 ^ (1 << 2); // Simulate a bit-flip error in memory
        #5 read_enable = 1;    // Enable read operation
        #5 read_enable = 0;    // Disable read operation

        // Finish simulation
        #5 $finish;
    end

    // Monitor outputs
    initial begin
        $monitor("At time %t, data_in = %b, data_out = %b, error_detected = %b, error_corrected = %b", 
                 $time, data_in, data_out, error_detected, error_corrected);
    end

    // Dump waveform for analysis
    initial begin
        $dumpfile("simulation.vcd");  // Specify VCD file for waveform output
        $dumpvars(0, testbench);      // Dump all signals in testbench
    end
endmodule

simulation.vcd
$date
	Tue Dec  3 04:54:39 2024
$end
$version
	Icarus Verilog
$end
$timescale
	1s
$end
$scope module testbench $end
$var wire 1 ! error_detected $end
$var wire 1 " error_corrected $end
$var wire 8 # data_out [7:0] $end
$var reg 4 $ address [3:0] $end
$var reg 8 % data_in [7:0] $end
$var reg 1 & read_enable $end
$var reg 1 ' write_enable $end
$scope module mem_edac $end
$var wire 4 ( address [3:0] $end
$var wire 8 ) data_in [7:0] $end
$var wire 8 * data_out [7:0] $end
$var wire 1 " error_corrected $end
$var wire 1 ! error_detected $end
$var wire 1 & read_enable $end
$var wire 1 ' write_enable $end
$var wire 12 + encoded_data [11:0] $end
$var wire 1 , detected_error $end
$var wire 8 - decoded_data [7:0] $end
$var wire 1 . corrected_error $end
$scope module decoder $end
$var wire 12 / encoded_data [11:0] $end
$var wire 1 0 p1 $end
$var wire 1 1 p2 $end
$var wire 1 2 p4 $end
$var wire 1 3 p8 $end
$var wire 4 4 syndrome [3:0] $end
$var reg 8 5 data_out [7:0] $end
$var reg 1 . error_corrected $end
$var reg 1 , error_detected $end
$upscope $end
$scope module encoder $end
$var wire 8 6 data_in [7:0] $end
$var wire 1 7 p1 $end
$var wire 1 8 p2 $end
$var wire 1 9 p4 $end
$var wire 1 : p8 $end
$var wire 12 ; encoded_data [11:0] $end
$upscope $end
$upscope $end
$upscope $end
$enddefinitions $end
$comment Show the parameter values. $end
$dumpall
$end
#0
$dumpvars
b10101101000 ;
0:
19
08
07
b10101010 6
bx 5
bx 4
x3
x2
x1
x0
bx /
x.
bx -
x,
b10101101000 +
bx *
b10101010 )
b0 (
0'
0&
b10101010 %
b0 $
bx #
x"
x!
$end
#5
10
11
12
b111 4
03
1"
1.
1!
1,
b10101101000 /
1'
#10
0'
#20
1&
#25
0&
#30
10
01
12
b1101 4
13
b10101 #
b10101 *
b10101 -
b10101 5
b101010101110 /
#35
1&
#40
0&
